{
    "Teams": [
        {
            "TeamName": "DZ",
            "Probability": 1.0,
            "Region": "NA"
        },
        {
            "TeamName": "BDS",
            "Probability": 1.0,
            "Region": "EU"
        },
        {
            "TeamName": "C9BC",
            "Probability": 1.0,
            "Region": "NA"
        },
        {
            "TeamName": "w7m",
            "Probability": 0.502578,
            "Region": "BR"
        },
        {
            "TeamName": "M80",
            "Probability": 0.999998,
            "Region": "NA"
        },
        {
            "TeamName": "FaZe",
            "Probability": 1.0,
            "Region": "BR"
        },
        {
            "TeamName": "Liquid",
            "Probability": 1.0,
            "Region": "BR"
        },
        {
            "TeamName": "Secret",
            "Probability": 1.0,
            "Region": "EU"
        },
        {
            "TeamName": "KS",
            "Probability": 0.032102,
            "Region": "BR"
        },
        {
            "TeamName": "SSG",
            "Probability": 0.700733,
            "Region": "NA"
        },
        {
            "TeamName": "SZ",
            "Probability": 0.997189,
            "Region": "JAPAN"
        },
        {
            "TeamName": "SQ",
            "Probability": 0.499298,
            "Region": "NA"
        },
        {
            "TeamName": "FURIA",
            "Probability": 0.99998,
            "Region": "BR"
        },
        {
            "TeamName": "CAG",
            "Probability": 0.498849,
            "Region": "JAPAN"
        },
        {
            "TeamName": "VP",
            "Probability": 0.498292,
            "Region": "EU"
        },
        {
            "TeamName": "ENCE",
            "Probability": 0.074485,
            "Region": "EU"
        },
        {
            "TeamName": "FOX",
            "Probability": 0.423178,
            "Region": "KOREA"
        },
        {
            "TeamName": "DK",
            "Probability": 0.522432,
            "Region": "KOREA"
        },
        {
            "TeamName": "Bleed",
            "Probability": 0.891152,
            "Region": "SEA"
        },
        {
            "TeamName": "PSG",
            "Probability": 0.645933,
            "Region": "KOREA"
        },
        {
            "TeamName": "GG",
            "Probability": 0.317833,
            "Region": "OCE"
        },
        {
            "TeamName": "ELV",
            "Probability": 0.155244,
            "Region": "SEA"
        },
        {
            "TeamName": "G2",
            "Probability": 0.086715,
            "Region": "EU"
        },
        {
            "TeamName": "E1",
            "Probability": 0.045426,
            "Region": "BR"
        },
        {
            "TeamName": "CTY",
            "Probability": 0.117157,
            "Region": "LATAM"
        },
        {
            "TeamName": "6K",
            "Probability": 0.065737,
            "Region": "LATAM"
        },
        {
            "TeamName": "FLCS",
            "Probability": 0.303839,
            "Region": "MENA"
        },
        {
            "TeamName": "OXG",
            "Probability": 0.090469,
            "Region": "NA"
        },
        {
            "TeamName": "WCG",
            "Probability": 0.089915,
            "Region": "NA"
        },
        {
            "TeamName": "CHIEFS",
            "Probability": 0.125711,
            "Region": "OCE"
        },
        {
            "TeamName": "BD",
            "Probability": 0.0083,
            "Region": "BR"
        },
        {
            "TeamName": "ALPHA",
            "Probability": 0.063582,
            "Region": "LATAM"
        },
        {
            "TeamName": "FNC",
            "Probability": 0.01631,
            "Region": "EU"
        },
        {
            "TeamName": "ITB",
            "Probability": 0.091127,
            "Region": "EU"
        },
        {
            "TeamName": "MIBR",
            "Probability": 0.032004,
            "Region": "BR"
        },
        {
            "TeamName": "NIP",
            "Probability": 0.008173,
            "Region": "BR"
        },
        {
            "TeamName": "WYLDE",
            "Probability": 0.013577,
            "Region": "EU"
        },
        {
            "TeamName": "ME",
            "Probability": 0.063088,
            "Region": "LATAM"
        },
        {
            "TeamName": "LOS",
            "Probability": 0.01139,
            "Region": "NA"
        },
        {
            "TeamName": "Fluxo",
            "Probability": 0.008204,
            "Region": "BR"
        }
    ]
}