{
    "Teams": [
        {
            "TeamName": "BDS",
            "Probability": 1.0,
            "Region": "EU"
        },
        {
            "TeamName": "Liquid",
            "Probability": 1.0,
            "Region": "BR"
        },
        {
            "TeamName": "FaZe",
            "Probability": 1.0,
            "Region": "BR"
        },
        {
            "TeamName": "C9BC",
            "Probability": 1.0,
            "Region": "NA"
        },
        {
            "TeamName": "M80",
            "Probability": 0.999999,
            "Region": "NA"
        },
        {
            "TeamName": "DZ",
            "Probability": 1.0,
            "Region": "NA"
        },
        {
            "TeamName": "CAG",
            "Probability": 0.497716,
            "Region": "JAPAN"
        },
        {
            "TeamName": "E1",
            "Probability": 0.046944,
            "Region": "BR"
        },
        {
            "TeamName": "Secret",
            "Probability": 1.0,
            "Region": "EU"
        },
        {
            "TeamName": "SZ",
            "Probability": 0.996989,
            "Region": "JAPAN"
        },
        {
            "TeamName": "FURIA",
            "Probability": 0.999978,
            "Region": "BR"
        },
        {
            "TeamName": "w7m",
            "Probability": 0.503986,
            "Region": "BR"
        },
        {
            "TeamName": "VP",
            "Probability": 0.498286,
            "Region": "EU"
        },
        {
            "TeamName": "SSG",
            "Probability": 0.699271,
            "Region": "NA"
        },
        {
            "TeamName": "G2",
            "Probability": 0.088316,
            "Region": "EU"
        },
        {
            "TeamName": "Bleed",
            "Probability": 0.88444,
            "Region": "SEA"
        },
        {
            "TeamName": "FOX",
            "Probability": 0.421765,
            "Region": "KOREA"
        },
        {
            "TeamName": "SQ",
            "Probability": 0.499722,
            "Region": "NA"
        },
        {
            "TeamName": "PSG",
            "Probability": 0.63424,
            "Region": "KOREA"
        },
        {
            "TeamName": "ENCE",
            "Probability": 0.075415,
            "Region": "EU"
        },
        {
            "TeamName": "FLCS",
            "Probability": 0.303688,
            "Region": "MENA"
        },
        {
            "TeamName": "DK",
            "Probability": 0.521116,
            "Region": "KOREA"
        },
        {
            "TeamName": "GG",
            "Probability": 0.305774,
            "Region": "OCE"
        },
        {
            "TeamName": "CTY",
            "Probability": 0.116451,
            "Region": "LATAM"
        },
        {
            "TeamName": "ELV",
            "Probability": 0.154912,
            "Region": "SEA"
        },
        {
            "TeamName": "ITB",
            "Probability": 0.09219,
            "Region": "EU"
        },
        {
            "TeamName": "WCG",
            "Probability": 0.074893,
            "Region": "NA"
        },
        {
            "TeamName": "CHIEFS",
            "Probability": 0.125447,
            "Region": "OCE"
        },
        {
            "TeamName": "LG",
            "Probability": 0.060732,
            "Region": "NA"
        },
        {
            "TeamName": "OXG",
            "Probability": 0.075362,
            "Region": "NA"
        },
        {
            "TeamName": "ME",
            "Probability": 0.063061,
            "Region": "LATAM"
        },
        {
            "TeamName": "6K",
            "Probability": 0.065471,
            "Region": "LATAM"
        },
        {
            "TeamName": "FNC",
            "Probability": 0.01634,
            "Region": "EU"
        },
        {
            "TeamName": "BD",
            "Probability": 0.008657,
            "Region": "BR"
        },
        {
            "TeamName": "KS",
            "Probability": 0.032981,
            "Region": "BR"
        },
        {
            "TeamName": "MIBR",
            "Probability": 0.032767,
            "Region": "BR"
        },
        {
            "TeamName": "LOS",
            "Probability": 0.009527,
            "Region": "NA"
        },
        {
            "TeamName": "NIP",
            "Probability": 0.008306,
            "Region": "BR"
        },
        {
            "TeamName": "ALPHA",
            "Probability": 0.063501,
            "Region": "LATAM"
        },
        {
            "TeamName": "Fluxo",
            "Probability": 0.008217,
            "Region": "BR"
        },
        {
            "TeamName": "WYLDE",
            "Probability": 0.01354,
            "Region": "EU"
        }
    ]
}